__init__.py
showlib/__init__.py
showlib/_version.py
showlib/config.py
showlib/netcdf.py
showlib/data/l0.yml
showlib/flights/__init__.py
showlib/flights/er2_2023/__init__.py
showlib/flights/er2_2023/convert_l1b.py
showlib/flights/er2_2023/convert_raw_l1a_to_l0_granules.py
showlib/flights/er2_2023/l0_to_l1a.py
showlib/flights/er2_2023/l1bdata.py
showlib/flights/er2_2023/Platform/ER2Platform.py
showlib/flights/er2_2023/Platform/__init__.py
showlib/flights/er2_2023/Specifications/__init__.py
showlib/flights/er2_2023/Specifications/er2_2023.yaml
showlib/flights/er2_2023/Specifications/shower2_specs.py
showlib/flights/er2_2023/l1a/__init__.py
showlib/flights/er2_2023/l1a/data.py
showlib/flights/er2_2023/l1a/l1a.py
showlib/flights/er2_2023/l1a/l1a_processing.py
showlib/l0/__init__.py
showlib/l0/data.py
showlib/l1b/data.py
showlib/l1b/l1b.py
showlib/l1b/l1b_processing.py
showlib/l2/ancillary.py
showlib/l2/data.py
showlib/l2/optical.py
showlib/l2/preprocessor.py
showlib/l2/shifts.py
showlib/l2/showmodel.py
showlib/l2/spline.py
showlib/l2/solar/__init__.py
showlib/l2/solar/kurucz.py
showlib/l2/solar/model.py
showlib/l2/solar/toon.py
showlib/por/l2/merra.py
showlib/por/l2/process.py
showlib/processing/__init__.py
showlib/processing/l1a_to_l1b.py
showlib/processing/l1b_to_l2.py
showlib-2025.2.1.dist-info/LICENSE
showlib-2025.2.1.dist-info/METADATA
showlib-2025.2.1.dist-info/WHEEL
showlib-2025.2.1.dist-info/top_level.txt
showlib-2025.2.1.dist-info/RECORD
